LICENSES/MIT.txt
capture2go/__init__.py
capture2go/ble.py
capture2go/device.py
capture2go/parsing.py
capture2go/pkg.py
capture2go/pkg.pyi
capture2go/usb.py
capture2go/utils.py
capture2go-1.0.0.dist-info/licenses/LICENSES/MIT.txt
docs/conf.py
examples/convert_to_mat.py
examples/download.py
examples/live_plot_example.py
examples/minimal_print_example.py
examples/realtime_streaming_example.py
examples/recording_example.py
capture2go-1.0.0.dist-info/METADATA
capture2go-1.0.0.dist-info/WHEEL
capture2go-1.0.0.dist-info/top_level.txt
capture2go-1.0.0.dist-info/RECORD
