Metadata-Version: 2.4
Name: capture2go
Version: 1.0.0
Summary: SDK for Capture2Go, the wearable sensor platform by SensorStim Neurotechnology GmbH.
Author-email: SensorStim Neurotechnology GmbH <support@capture2go.com>
License-Expression: MIT
Project-URL: Homepage, https://capture2go.com
Classifier: Programming Language :: Python :: 3
Classifier: Operating System :: OS Independent
Requires-Python: >=3.10
License-File: LICENSES/MIT.txt
Requires-Dist: numpy
Requires-Dist: bleak
Requires-Dist: pyserial
Provides-Extra: docs
Requires-Dist: sphinx>=7.0; extra == "docs"
Requires-Dist: sphinx-rtd-theme>=2.0.0; extra == "docs"
Requires-Dist: myst-parser>=3.0.0; extra == "docs"
Requires-Dist: sphinxcontrib-mermaid>=0.9.2; extra == "docs"
Dynamic: license-file
